db_frostyfeet909/__init__.py
db_frostyfeet909/main.py
db_frostyfeet909-0.0.8.dist-info/LICENSE
db_frostyfeet909-0.0.8.dist-info/METADATA
db_frostyfeet909-0.0.8.dist-info/WHEEL
db_frostyfeet909-0.0.8.dist-info/top_level.txt
db_frostyfeet909-0.0.8.dist-info/RECORD
