Metadata-Version: 2.1
Name: db-frostyfeet909
Version: 0.0.8
Summary: A db interface.
Author-email: Algernon Sampson <algiesampson@gmail.com>
Project-URL: Homepage, https://github.com/frostyfeet909/db_frostyfeet909
Project-URL: Bug Tracker, https://github.com/frostyfeet909/db_frostyfeet909/issues
Classifier: Programming Language :: Python :: 3.10
Classifier: License :: OSI Approved :: GNU General Public License v3 (GPLv3)
Classifier: Operating System :: OS Independent
Requires-Python: ~=3.10
License-File: LICENSE
Requires-Dist: psycopg2-binary (==2.9.5)
Requires-Dist: SQLAlchemy (==1.4.42)
Requires-Dist: sqlalchemy-utils (==0.38.0)
